ApacheHive311ZhongwenWendang/README.md
ApacheHive311ZhongwenWendang/__init__.py
ApacheHive311ZhongwenWendang/__main__.py
ApacheHive311ZhongwenWendang/file.epub
ApacheHive311ZhongwenWendang/index.html
ApacheHive311ZhongwenWendang/css/__init__.py
ApacheHive311ZhongwenWendang/css/annotations.css
ApacheHive311ZhongwenWendang/css/main.css
ApacheHive311ZhongwenWendang/css/normalize.css
ApacheHive311ZhongwenWendang/css/popup.css
ApacheHive311ZhongwenWendang/font/__init__.py
ApacheHive311ZhongwenWendang/font/fontello.eot
ApacheHive311ZhongwenWendang/font/fontello.svg
ApacheHive311ZhongwenWendang/font/fontello.ttf
ApacheHive311ZhongwenWendang/font/fontello.woff
ApacheHive311ZhongwenWendang/img/__init__.py
ApacheHive311ZhongwenWendang/img/annotator-glyph-sprite.png
ApacheHive311ZhongwenWendang/img/annotator-icon-sprite.png
ApacheHive311ZhongwenWendang/img/apple-touch-icon.png
ApacheHive311ZhongwenWendang/img/cancelfullscreen.png
ApacheHive311ZhongwenWendang/img/close.png
ApacheHive311ZhongwenWendang/img/fullscreen.png
ApacheHive311ZhongwenWendang/img/loader.gif
ApacheHive311ZhongwenWendang/img/menu-icon.png
ApacheHive311ZhongwenWendang/img/save.png
ApacheHive311ZhongwenWendang/img/saved.png
ApacheHive311ZhongwenWendang/img/settings-s.png
ApacheHive311ZhongwenWendang/img/settings.png
ApacheHive311ZhongwenWendang/img/star.png
ApacheHive311ZhongwenWendang/js/__init__.py
ApacheHive311ZhongwenWendang/js/epub.js
ApacheHive311ZhongwenWendang/js/epub.min.js
ApacheHive311ZhongwenWendang/js/epub.min.map
ApacheHive311ZhongwenWendang/js/hooks.min.js
ApacheHive311ZhongwenWendang/js/hooks.min.map
ApacheHive311ZhongwenWendang/js/reader.js
ApacheHive311ZhongwenWendang/js/reader.js.map
ApacheHive311ZhongwenWendang/js/reader.min.js
ApacheHive311ZhongwenWendang/js/reader.min.map
ApacheHive311ZhongwenWendang/js/hooks/__init__.py
ApacheHive311ZhongwenWendang/js/hooks/extensions/__init__.py
ApacheHive311ZhongwenWendang/js/hooks/extensions/highlight.js
apache_hive_3_1_1_zhongwen_wendang-2024.3.4.0.dist-info/METADATA
apache_hive_3_1_1_zhongwen_wendang-2024.3.4.0.dist-info/WHEEL
apache_hive_3_1_1_zhongwen_wendang-2024.3.4.0.dist-info/entry_points.txt
apache_hive_3_1_1_zhongwen_wendang-2024.3.4.0.dist-info/top_level.txt
apache_hive_3_1_1_zhongwen_wendang-2024.3.4.0.dist-info/RECORD
